particleShield/src/__init__.py
particleShield/src/particleShield.py
particleShield-0.0.4.dist-info/LICENCE.txt
particleShield-0.0.4.dist-info/METADATA
particleShield-0.0.4.dist-info/WHEEL
particleShield-0.0.4.dist-info/top_level.txt
particleShield-0.0.4.dist-info/RECORD
