Metadata-Version: 2.1
Name: particleShield
Version: 0.0.4
Summary: Package for radiation shielding modelling.
Author-email: Pragan Yadav <ypragyan01@gmail.com>
Project-URL: Homepage, https://github.com/ypragyan/ParticleShield
Classifier: Programming Language :: Python :: 3
Classifier: License :: OSI Approved :: MIT License
Classifier: Operating System :: OS Independent
Classifier: Programming Language :: Python :: 3
Classifier: Topic :: Scientific/Engineering
Classifier: Topic :: Scientific/Engineering :: Physics
Classifier: Intended Audience :: Science/Research
Classifier: Intended Audience :: Healthcare Industry
Requires-Python: >=3.7
License-File: LICENCE.txt
